<Interface xmlns:xsi="http://www.w3.org/2001/XMLSchema-instance" xsi:noNamespaceSchemaLocation="../../Interface.xsd">
    <Scripts>
        <Script file="Source/SalvagingWindow.lua" />
    </Scripts>
    <Windows>
        <Window name="SalvagingWindow" movable="true" layer="popup" handleinput="true">
            <Size>
                <AbsPoint x="350" y="225" />
            </Size>
            <Anchors>
                <Anchor point="topleft" relativePoint="topleft">
                    <AbsPoint x="480" y="620" />
                </Anchor>
            </Anchors>
            <EventHandlers>
                <EventHandler event="OnInitialize" function="SalvagingWindow.Initialize" />
                <EventHandler event="OnShutdown" function="SalvagingWindow.Shutdown" />
                <EventHandler event="OnRButtonUp" function="SalvagingWindow.OnRButtonUp" />
            </EventHandlers>
            <Windows>
                <!-- STANDARD WINDOW FRAME -->
                <Window name="$parentTitleBar" inherits="EA_TitleBar_Default" />
                
                <Window name="$parentBackground" inherits="EA_Window_DefaultFrame" >
                    <Anchors>
                        <Anchor point="topleft" relativePoint="topleft" >
                            <AbsPoint x="0" y="32" />
                        </Anchor>
                        <Anchor point="bottomright" relativePoint="bottomright" />
                    </Anchors>
                </Window>
                
                <!-- Close Button -->
                <Button name="$parentClose" inherits="EA_Button_DefaultWindowClose">
                    <EventHandlers>
                        <EventHandler event="OnLButtonUp" function="SalvagingWindow.Hide" />
                    </EventHandlers>
                </Button>
                
                <Label name="$parentChoiceText" font="font_default_text" textalign="left" handleinput="true" autoresize="true" wordwrap="true">
                    <Size>
                        <AbsPoint x="300" y="32" />
                    </Size>
                    <Color r="255" g="255" b="255" a="255" />
                    <Anchors>
                        <Anchor point="top" relativePoint="top" >
                            <AbsPoint x="0" y="50" />
                        </Anchor>
                    </Anchors>
                </Label>
                
                <Button name="$parentAccept" inherits="EA_Button_DefaultResizeable" >
                    <Size>
                        <AbsPoint x="125" y="39" />
                    </Size>
                    <EventHandlers>
                        <EventHandler event="OnLButtonUp" function="SalvagingWindow.OnAcceptLButtonUp" />
                    </EventHandlers>
                    <Anchors>
                        <Anchor point="bottomleft" relativePoint="bottomleft" >
                            <AbsPoint x="25" y="-15" />
                        </Anchor>
                    </Anchors>
                </Button>
                <Button name="$parentCancel" inherits="EA_Button_DefaultResizeable" >
                    <Size>
                        <AbsPoint x="125" y="39" />
                    </Size>
                    <EventHandlers>
                        <EventHandler event="OnLButtonUp" function="SalvagingWindow.OnCancelLButtonUp" />
                    </EventHandlers>
                    <Anchors>
                        <Anchor point="bottomright" relativePoint="bottomright" >
                            <AbsPoint x="-25" y="-15" />
                        </Anchor>
                    </Anchors>
                </Button>
                
                <!-- Stats will be added dynamically -->
                
            </Windows>
        </Window>

    </Windows>
</Interface>
